uart_tx.v
module uart_tx (
    input  wire       clk,
    input  wire       rst,
    input  wire       tx_start,
    input  wire [7:0] data,

    output reg        tx,
    output reg        tx_done
);

    // Definición de estados
    localparam IDLE  = 2'b00;
    localparam START = 2'b01;
    localparam DATA  = 2'b10;
    localparam STOP  = 2'b11;

    reg [1:0] current_state;

    // Registro para almacenar el dato
    reg [7:0] data_reg;

    // Contador de bits
    reg [2:0] bit_count;

    // FSM principal
    always @(posedge clk or posedge rst) begin

        if (rst) begin
            current_state <= IDLE;
            data_reg      <= 8'b0;
            bit_count     <= 3'b0;
            tx            <= 1'b1;
            tx_done       <= 1'b0;

        end else begin

            // Valor por defecto
            tx_done <= 1'b0;

            case (current_state)

                IDLE: begin
                    tx <= 1'b1;

                    if (tx_start) begin
                        data_reg      <= data;
                        bit_count     <= 3'b0;
                        current_state <= START;
                    end
                end

                START: begin
                    tx <= 1'b0;
                    current_state <= DATA;
                end

                DATA: begin
                    tx <= data_reg[bit_count];

                    if (bit_count == 3'd7) begin
                        current_state <= STOP;
                    end else begin
                        bit_count <= bit_count + 1'b1;
                    end
                end

                STOP: begin
                    tx <= 1'b1;
                    tx_done <= 1'b1;
                    current_state <= IDLE;
                end

                default: begin
                    current_state <= IDLE;
                end

            endcase

        end

    end

endmodule

tb_uart_tx.v
`timescale 1ns/1ps

module tb_uart_tx;

    // Señales de prueba
    reg clk = 0;
    reg rst = 0;
    reg tx_start = 0;
    reg [7:0] data = 8'h00;

    wire tx;
    wire tx_done;

    // Periodo de reloj
    localparam CLK_PERIOD = 10;

    // Instancia del DUT
    uart_tx DUT (
        .clk(clk),
        .rst(rst),
        .tx_start(tx_start),
        .data(data),
        .tx(tx),
        .tx_done(tx_done)
    );

    // Generador de reloj
    always #(CLK_PERIOD/2) clk = ~clk;

    // Estímulos
    initial begin
        // Configuración para generar las ondas
        $dumpfile("tb_uart_tx.vcd");
        $dumpvars(0, tb_uart_tx);

        // RESET
        $display("Aplicando reset...");
        rst = 1'b1;
        #30;
        rst = 1'b0;
        #20;

        // PRIMERA TRANSMISION
        $display("Transmitiendo dato xAA");
        data = 8'hAA;
        tx_start = 1'b1;
        #CLK_PERIOD;
        tx_start = 1'b0;

        // Esperar fin de transmisión
        @(posedge tx_done);
        $display("Transmision 1 completada");
        #50;

        // SEGUNDA TRANSMISION
        $display("Transmitiendo dato x55");
        data = 8'h55;
        tx_start = 1'b1;
        #CLK_PERIOD;
        tx_start = 1'b0;

        @(posedge tx_done);
        $display("Transmision 2 completada");
        #50;

        // TERCERA TRANSMISION
        $display("Transmitiendo dato xF0");
        data = 8'hF0;
        tx_start = 1'b1;
        #CLK_PERIOD;
        tx_start = 1'b0;

        @(posedge tx_done);
        $display("Transmision 3 completada");
        #50;

        $display("SIMULACION FINALIZADA");
        $finish;
    end

endmodule

tb_uart_tx.vcd
$date
	Sun Jun 14 20:23:46 2026
$end
$version
	Icarus Verilog
$end
$timescale
	1ps
$end
$scope module tb_uart_tx $end
$var wire 1 ! tx_done $end
$var wire 1 " tx $end
$var parameter 32 # CLK_PERIOD $end
$var reg 1 $ clk $end
$var reg 8 % data [7:0] $end
$var reg 1 & rst $end
$var reg 1 ' tx_start $end
$scope module DUT $end
$var wire 1 $ clk $end
$var wire 8 ( data [7:0] $end
$var wire 1 & rst $end
$var wire 1 ' tx_start $end
$var parameter 2 ) DATA $end
$var parameter 2 * IDLE $end
$var parameter 2 + START $end
$var parameter 2 , STOP $end
$var reg 3 - bit_count [2:0] $end
$var reg 2 . current_state [1:0] $end
$var reg 8 / data_reg [7:0] $end
$var reg 1 " tx $end
$var reg 1 ! tx_done $end
$upscope $end
$upscope $end
$enddefinitions $end
$comment Show the parameter values. $end
$dumpall
b11 ,
b1 +
b0 *
b10 )
b1010 #
$end
#0
$dumpvars
b0 /
b0 .
b0 -
b0 (
0'
1&
b0 %
0$
1"
0!
$end
#5000
1$
#10000
0$
#15000
1$
#20000
0$
#25000
1$
#30000
0$
0&
#35000
1$
#40000
0$
#45000
1$
#50000
0$
1'
b10101010 %
b10101010 (
#55000
b1 .
b10101010 /
1$
#60000
0$
0'
#65000
b10 .
0"
1$
#70000
0$
#75000
b1 -
1$
#80000
0$
#85000
b10 -
1"
1$
#90000
0$
#95000
b11 -
0"
1$
#100000
0$
#105000
b100 -
1"
1$
#110000
0$
#115000
b101 -
0"
1$
#120000
0$
#125000
b110 -
1"
1$
#130000
0$
#135000
b111 -
0"
1$
#140000
0$
#145000
b11 .
1"
1$
#150000
0$
#155000
b0 .
1!
1$
#160000
0$
#165000
0!
1$
#170000
0$
#175000
1$
#180000
0$
#185000
1$
#190000
0$
#195000
1$
#200000
0$
#205000
b1 .
b0 -
b1010101 /
1$
1'
b1010101 %
b1010101 (
#210000
0$
#215000
b10 .
0"
1$
0'
#220000
0$
#225000
b1 -
1"
1$
#230000
0$
#235000
b10 -
0"
1$
#240000
0$
#245000
b11 -
1"
1$
#250000
0$
#255000
b100 -
0"
1$
#260000
0$
#265000
b101 -
1"
1$
#270000
0$
#275000
b110 -
0"
1$
#280000
0$
#285000
b111 -
1"
1$
#290000
0$
#295000
b11 .
0"
1$
#300000
0$
#305000
b0 .
1!
1"
1$
#310000
0$
#315000
0!
1$
#320000
0$
#325000
1$
#330000
0$
#335000
1$
#340000
0$
#345000
1$
#350000
0$
#355000
b1 .
b0 -
b11110000 /
1$
1'
b11110000 %
b11110000 (
#360000
0$
#365000
b10 .
0"
1$
0'
#370000
0$
#375000
b1 -
1$
#380000
0$
#385000
b10 -
1$
#390000
0$
#395000
b11 -
1$
#400000
0$
#405000
b100 -
1$
#410000
0$
#415000
b101 -
1"
1$
#420000
0$
#425000
b110 -
1$
#430000
0$
#435000
b111 -
1$
#440000
0$
#445000
b11 .
1$
#450000
0$
#455000
b0 .
1!
1$
#460000
0$
#465000
0!
1$
