uart_rx.v
module uart_rx (
    input  wire       clk,
    input  wire       rst,
    input  wire       rx,

    output reg [7:0] data_out,
    output reg       rx_done
);

    // Estados de la FSM
    localparam IDLE  = 2'b00;
    localparam START = 2'b01;
    localparam DATA  = 2'b10;
    localparam STOP  = 2'b11;

    reg [1:0] current_state;

    // Registro para almacenar el dato recibido
    reg [7:0] data_reg;

    // Contador de bits
    reg [2:0] bit_count;

    // FSM principal
    always @(posedge clk or posedge rst) begin

        if (rst) begin
            current_state <= IDLE;
            data_reg      <= 8'b0;
            bit_count     <= 3'b0;

            data_out      <= 8'b0;
            rx_done       <= 1'b0;

        end else begin

            rx_done <= 1'b0;

            case (current_state)

                // Espera de una transmisión
                IDLE: begin
                    if (rx == 1'b0)
                        current_state <= START;
                end

                // Confirmación del bit de inicio
                START: begin
                    bit_count <= 3'b0;
                    current_state <= DATA;
                end

                // Recepción de datos
                DATA: begin

                    data_reg[bit_count] <= rx;

                    if (bit_count == 3'd7)
                        current_state <= STOP;
                    else
                        bit_count <= bit_count + 1'b1;

                end

                // Verificación del bit de parada
                STOP: begin

                    if (rx == 1'b1) begin
                        data_out <= data_reg;
                        rx_done  <= 1'b1;
                    end

                    current_state <= IDLE;

                end

                default: begin
                    current_state <= IDLE;
                end

            endcase

        end

    end

endmodule

tb_uart_rx.v
`timescale 1ns/1ps

module tb_uart_rx;

    reg clk = 0;
    reg rst = 0;
    reg rx  = 1;

    wire [7:0] data_out;
    wire rx_done;

    localparam CLK_PERIOD = 10;

    // DUT
    uart_rx DUT (
        .clk(clk),
        .rst(rst),
        .rx(rx),
        .data_out(data_out),
        .rx_done(rx_done)
    );

    // Generador de reloj
    always #(CLK_PERIOD/2) clk = ~clk;

    // Estímulos
    initial begin
        // Configuración para generar las ondas
        $dumpfile("tb_uart_rx.vcd");
        $dumpvars(0, tb_uart_rx);

        // RESET
        rst = 1'b1;
        #30;

        rst = 1'b0;
        #30;

        // Recepción de xAA
        $display("Enviando trama xAA");

        rx = 1'b0; #CLK_PERIOD; // START

        rx = 1'b0; #CLK_PERIOD; // bit0
        rx = 1'b1; #CLK_PERIOD; // bit1
        rx = 1'b0; #CLK_PERIOD; // bit2
        rx = 1'b1; #CLK_PERIOD; // bit3
        rx = 1'b0; #CLK_PERIOD; // bit4
        rx = 1'b1; #CLK_PERIOD; // bit5
        rx = 1'b0; #CLK_PERIOD; // bit6
        rx = 1'b1; #CLK_PERIOD; // bit7

        rx = 1'b1; #CLK_PERIOD; // STOP

        @(posedge rx_done);

        $display("Byte recibido correctamente");
        $display("Dato recibido = %h", data_out);

        #50;

        // Recepción de x55
        $display("Enviando trama x55");

        rx = 1'b0; #CLK_PERIOD; // START

        rx = 1'b1; #CLK_PERIOD; // bit0
        rx = 1'b0; #CLK_PERIOD; // bit1
        rx = 1'b1; #CLK_PERIOD; // bit2
        rx = 1'b0; #CLK_PERIOD; // bit3
        rx = 1'b1; #CLK_PERIOD; // bit4
        rx = 1'b0; #CLK_PERIOD; // bit5
        rx = 1'b1; #CLK_PERIOD; // bit6
        rx = 1'b0; #CLK_PERIOD; // bit7

        rx = 1'b1; #CLK_PERIOD; // STOP

        @(posedge rx_done);

        $display("Segunda recepción completada");
        $display("Dato recibido = %h", data_out);

        #50;

        $display("SIMULACION FINALIZADA");

        $finish;

    end

endmodule

tb_uart_rx.vcd
$date
	Sun Jun 14 20:40:08 2026
$end
$version
	Icarus Verilog
$end
$timescale
	1ps
$end
$scope module tb_uart_rx $end
$var wire 1 ! rx_done $end
$var wire 8 " data_out [7:0] $end
$var parameter 32 # CLK_PERIOD $end
$var reg 1 $ clk $end
$var reg 1 % rst $end
$var reg 1 & rx $end
$scope module DUT $end
$var wire 1 $ clk $end
$var wire 1 % rst $end
$var wire 1 & rx $end
$var parameter 2 ' DATA $end
$var parameter 2 ( IDLE $end
$var parameter 2 ) START $end
$var parameter 2 * STOP $end
$var reg 3 + bit_count [2:0] $end
$var reg 2 , current_state [1:0] $end
$var reg 8 - data_out [7:0] $end
$var reg 8 . data_reg [7:0] $end
$var reg 1 ! rx_done $end
$upscope $end
$upscope $end
$enddefinitions $end
$comment Show the parameter values. $end
$dumpall
b11 *
b1 )
b0 (
b10 '
b1010 #
$end
#0
$dumpvars
b0 .
b0 -
b0 ,
b0 +
1&
1%
0$
b0 "
0!
$end
#5000
1$
#10000
0$
#15000
1$
#20000
0$
#25000
1$
#30000
0$
0%
#35000
1$
#40000
0$
#45000
1$
#50000
0$
#55000
1$
#60000
0$
0&
#65000
b1 ,
1$
#70000
0$
#75000
b10 ,
1$
#80000
0$
1&
#85000
b1 +
b1 .
1$
#90000
0$
0&
#95000
b10 +
1$
#100000
0$
1&
#105000
b11 +
b101 .
1$
#110000
0$
0&
#115000
b100 +
1$
#120000
0$
1&
#125000
b101 +
b10101 .
1$
#130000
0$
0&
#135000
b110 +
1$
#140000
0$
1&
#145000
b111 +
b1010101 .
1$
#150000
0$
#155000
b11 ,
b11010101 .
1$
#160000
0$
#165000
b0 ,
1!
b11010101 "
b11010101 -
1$
#170000
0$
#175000
0!
1$
#180000
0$
#185000
1$
#190000
0$
#195000
1$
#200000
0$
#205000
1$
#210000
0$
#215000
b1 ,
1$
0&
#220000
0$
#225000
b10 ,
b0 +
1$
1&
#230000
0$
#235000
b1 +
b11010100 .
1$
0&
#240000
0$
#245000
b10 +
b11010110 .
1$
1&
#250000
0$
#255000
b11 +
b11010010 .
1$
0&
#260000
0$
#265000
b100 +
b11011010 .
1$
1&
#270000
0$
#275000
b101 +
b11001010 .
1$
0&
#280000
0$
#285000
b110 +
b11101010 .
1$
1&
#290000
0$
#295000
b111 +
b10101010 .
1$
0&
#300000
0$
#305000
b11 ,
1$
1&
#310000
0$
#315000
b0 ,
1!
b10101010 "
b10101010 -
1$
#320000
0$
#325000
0!
1$
